pyix/__init__.py
pyix-0.1.0.dist-info/METADATA
pyix-0.1.0.dist-info/WHEEL
pyix-0.1.0.dist-info/RECORD
